{"SURVIVAL":{"enderChestContents":{},"armorContents":{},"balance":"100.0","potions":"[]","inventoryContents":{"10":{"==":"org.bukkit.inventory.ItemStack","type":"NETHER_STALK","amount":2},"17":{"==":"org.bukkit.inventory.ItemStack","type":"DIAMOND","amount":3},"9":{"==":"org.bukkit.inventory.ItemStack","type":"MELON_SEEDS"},"13":{"==":"org.bukkit.inventory.ItemStack","type":"CARROT_ITEM","amount":6},"14":{"==":"org.bukkit.inventory.ItemStack","type":"SEEDS","amount":2},"28":{"==":"org.bukkit.inventory.ItemStack","type":"ARROW","amount":2},"11":{"==":"org.bukkit.inventory.ItemStack","type":"SUGAR_CANE","amount":2},"12":{"==":"org.bukkit.inventory.ItemStack","type":"POTATO_ITEM","amount":2}},"stats":{"ra":"300","ex":"0.7188363","hp":"20","txp":"13","fl":"17","el":"0","sa":"0.0","ma":"300","xp":"0.7647059","ft":"-20","fd":"0.0"}}}