{"SURVIVAL":{"armorContents":{},"balance":"100.0","enderChestContents":{},"inventoryContents":{"19":{"==":"org.bukkit.inventory.ItemStack","type":"COBBLESTONE","amount":10},"35":{"==":"org.bukkit.inventory.ItemStack","type":"COBBLESTONE","amount":64},"17":{"==":"org.bukkit.inventory.ItemStack","type":"FURNACE","amount":7},"18":{"==":"org.bukkit.inventory.ItemStack","type":"WOOD_DOOR"},"33":{"==":"org.bukkit.inventory.ItemStack","type":"BONE","amount":2},"15":{"==":"org.bukkit.inventory.ItemStack","type":"FLOWER_POT_ITEM","amount":4},"34":{"==":"org.bukkit.inventory.ItemStack","type":"ARROW","amount":2},"16":{"==":"org.bukkit.inventory.ItemStack","type":"FENCE","amount":8},"13":{"==":"org.bukkit.inventory.ItemStack","type":"REDSTONE_TORCH_ON","amount":2},"14":{"==":"org.bukkit.inventory.ItemStack","type":"RED_ROSE","amount":4},"11":{"==":"org.bukkit.inventory.ItemStack","type":"WOOD_STAIRS","amount":3},"12":{"==":"org.bukkit.inventory.ItemStack","type":"TORCH","amount":10},"21":{"==":"org.bukkit.inventory.ItemStack","type":"WOOD_DOOR"},"20":{"==":"org.bukkit.inventory.ItemStack","type":"WOOD","amount":2},"22":{"==":"org.bukkit.inventory.ItemStack","type":"WOOD_DOOR"},"23":{"==":"org.bukkit.inventory.ItemStack","type":"DIAMOND_SWORD"},"24":{"==":"org.bukkit.inventory.ItemStack","type":"WOOD_STEP","amount":12},"25":{"==":"org.bukkit.inventory.ItemStack","type":"WOOD","damage":1,"amount":8},"26":{"==":"org.bukkit.inventory.ItemStack","type":"REDSTONE","amount":5},"27":{"==":"org.bukkit.inventory.ItemStack","type":"STONE_HOE","meta":{"==":"ItemMeta","meta-type":"UNSPECIFIC","display-name":"§bStarter Hoe"}},"28":{"==":"org.bukkit.inventory.ItemStack","type":"SIGN","amount":2},"29":{"==":"org.bukkit.inventory.ItemStack","type":"SAPLING","amount":5},"3":{"==":"org.bukkit.inventory.ItemStack","type":"STONE_AXE","damage":49,"meta":{"==":"ItemMeta","meta-type":"UNSPECIFIC","display-name":"§bStarter Axe"}},"2":{"==":"org.bukkit.inventory.ItemStack","type":"STONE_PICKAXE","damage":111,"meta":{"==":"ItemMeta","meta-type":"UNSPECIFIC","display-name":"§bStarter Pickaxe"}},"10":{"==":"org.bukkit.inventory.ItemStack","type":"WORKBENCH","amount":4},"1":{"==":"org.bukkit.inventory.ItemStack","type":"STONE_SPADE","meta":{"==":"ItemMeta","meta-type":"UNSPECIFIC","display-name":"§bStarter Shovel"}},"0":{"==":"org.bukkit.inventory.ItemStack","type":"STONE_SWORD","damage":4,"meta":{"==":"ItemMeta","meta-type":"UNSPECIFIC","display-name":"§bStarter Sword"}},"30":{"==":"org.bukkit.inventory.ItemStack","type":"LOG","damage":2,"amount":5},"7":{"==":"org.bukkit.inventory.ItemStack","type":"COAL","amount":27},"6":{"==":"org.bukkit.inventory.ItemStack","type":"CHEST","amount":8},"32":{"==":"org.bukkit.inventory.ItemStack","type":"SAPLING","damage":2},"5":{"==":"org.bukkit.inventory.ItemStack","type":"WOOD_DOOR"},"31":{"==":"org.bukkit.inventory.ItemStack","type":"APPLE"},"4":{"==":"org.bukkit.inventory.ItemStack","type":"BREAD","amount":17},"8":{"==":"org.bukkit.inventory.ItemStack","type":"LOG","amount":4}},"potions":"[]","stats":{"ra":"300","ex":"1.9809207","hp":"20","txp":"0","fl":"13","el":"0","ma":"300","sa":"0.0","xp":"0.0","ft":"-20","fd":"0.0"}}}