{"SURVIVAL":{"enderChestContents":{},"balance":"30.1","inventoryContents":{"19":{"==":"org.bukkit.inventory.ItemStack","type":"BONE","amount":5},"35":{"==":"org.bukkit.inventory.ItemStack","type":"PORK","amount":3},"17":{"==":"org.bukkit.inventory.ItemStack","type":"COBBLESTONE","amount":18},"18":{"==":"org.bukkit.inventory.ItemStack","type":"ROTTEN_FLESH","amount":11},"33":{"==":"org.bukkit.inventory.ItemStack","type":"SPIDER_EYE","amount":4},"15":{"==":"org.bukkit.inventory.ItemStack","type":"FURNACE"},"34":{"==":"org.bukkit.inventory.ItemStack","type":"WOOD","damage":2},"16":{"==":"org.bukkit.inventory.ItemStack","type":"WOOD_DOOR"},"13":{"==":"org.bukkit.inventory.ItemStack","type":"FEATHER"},"14":{"==":"org.bukkit.inventory.ItemStack","type":"SANDSTONE","amount":2},"11":{"==":"org.bukkit.inventory.ItemStack","type":"SUGAR_CANE","amount":51},"12":{"==":"org.bukkit.inventory.ItemStack","type":"LEATHER","amount":7},"21":{"==":"org.bukkit.inventory.ItemStack","type":"SAPLING"},"20":{"==":"org.bukkit.inventory.ItemStack","type":"ARROW","amount":5},"22":{"==":"org.bukkit.inventory.ItemStack","type":"DIRT"},"23":{"==":"org.bukkit.inventory.ItemStack","type":"STICK","amount":4},"24":{"==":"org.bukkit.inventory.ItemStack","type":"CARROT_ITEM","amount":22},"25":{"==":"org.bukkit.inventory.ItemStack","type":"SEEDS","amount":64},"26":{"==":"org.bukkit.inventory.ItemStack","type":"POTATO_ITEM","amount":28},"27":{"==":"org.bukkit.inventory.ItemStack","type":"STRING","amount":16},"28":{"==":"org.bukkit.inventory.ItemStack","type":"WOOD_SWORD","damage":59},"29":{"==":"org.bukkit.inventory.ItemStack","type":"LADDER","amount":3},"3":{"==":"org.bukkit.inventory.ItemStack","type":"BREAD","amount":13},"2":{"==":"org.bukkit.inventory.ItemStack","type":"WOOD_PICKAXE","damage":43},"10":{"==":"org.bukkit.inventory.ItemStack","type":"EGG"},"1":{"==":"org.bukkit.inventory.ItemStack","type":"SAND","amount":11},"30":{"==":"org.bukkit.inventory.ItemStack","type":"TORCH","amount":19},"7":{"==":"org.bukkit.inventory.ItemStack","type":"SUGAR_CANE","amount":64},"6":{"==":"org.bukkit.inventory.ItemStack","type":"WORKBENCH"},"32":{"==":"org.bukkit.inventory.ItemStack","type":"COAL","amount":15},"5":{"==":"org.bukkit.inventory.ItemStack","type":"BED"},"31":{"==":"org.bukkit.inventory.ItemStack","type":"RAW_BEEF","amount":3},"4":{"==":"org.bukkit.inventory.ItemStack","type":"SEEDS","amount":64},"9":{"==":"org.bukkit.inventory.ItemStack","type":"FENCE","amount":2},"8":{"==":"org.bukkit.inventory.ItemStack","type":"WHEAT","amount":4}},"potions":"[]","armorContents":{},"stats":{"ra":"300","ex":"3.1568975","hp":"20","fl":"20","txp":"231","el":"13","ma":"300","sa":"5.0","xp":"0.58823556","ft":"-20","fd":"0.0"}}}