{"SURVIVAL":{"enderChestContents":{},"inventoryContents":{"2":{"==":"org.bukkit.inventory.ItemStack","type":"GOLD_NUGGET","amount":2},"1":{"==":"org.bukkit.inventory.ItemStack","type":"BOW","damage":1,"meta":{"==":"ItemMeta","meta-type":"UNSPECIFIC","enchants":{"DURABILITY":1,"ARROW_DAMAGE":1},"repair-cost":2}},"0":{"==":"org.bukkit.inventory.ItemStack","type":"DIAMOND_SWORD","damage":308,"meta":{"==":"ItemMeta","meta-type":"UNSPECIFIC","enchants":{"DAMAGE_ARTHROPODS":1}}}},"armorContents":{"3":{"==":"org.bukkit.inventory.ItemStack","type":"DIAMOND_HELMET","damage":41},"2":{"==":"org.bukkit.inventory.ItemStack","type":"DIAMOND_CHESTPLATE","damage":195},"1":{"==":"org.bukkit.inventory.ItemStack","type":"DIAMOND_LEGGINGS","damage":195},"0":{"==":"org.bukkit.inventory.ItemStack","type":"DIAMOND_BOOTS","damage":41}},"potions":"[]","balance":"20.34689426166091","stats":{"ex":"2.887343","ra":"300","hp":"1","txp":"1417","fl":"13","el":"5","sa":"0.0","ma":"300","xp":"0.3367144","ft":"-20","fd":"0.0"}}}