{"SURVIVAL":{"potions":"[]","balance":"269.0","enderChestContents":{},"inventoryContents":{"20":{"==":"org.bukkit.inventory.ItemStack","type":"IRON_ORE","amount":3},"2":{"==":"org.bukkit.inventory.ItemStack","type":"BREAD","amount":23},"10":{"==":"org.bukkit.inventory.ItemStack","type":"COAL","amount":2},"1":{"==":"org.bukkit.inventory.ItemStack","type":"STONE_AXE","damage":85,"meta":{"==":"ItemMeta","meta-type":"UNSPECIFIC","display-name":"§bStarter Axe"}},"0":{"==":"org.bukkit.inventory.ItemStack","type":"IRON_PICKAXE","damage":18},"19":{"==":"org.bukkit.inventory.ItemStack","type":"DIAMOND","amount":4},"35":{"==":"org.bukkit.inventory.ItemStack","type":"WOOD","amount":10},"17":{"==":"org.bukkit.inventory.ItemStack","type":"COBBLESTONE","amount":33},"18":{"==":"org.bukkit.inventory.ItemStack","type":"GOLD_INGOT","amount":4},"9":{"==":"org.bukkit.inventory.ItemStack","type":"IRON_INGOT","amount":5},"26":{"==":"org.bukkit.inventory.ItemStack","type":"LOG","amount":34},"11":{"==":"org.bukkit.inventory.ItemStack","type":"GOLD_ORE","amount":3}},"armorContents":{},"stats":{"ex":"0.6633559","ra":"300","hp":"20","fl":"20","txp":"282","el":"16","ma":"300","sa":"4.0","xp":"0.4999999","ft":"-20","fd":"0.0"}}}