{"SURVIVAL":{"balance":"27925.0","inventoryContents":{"1":{"==":"org.bukkit.inventory.ItemStack","type":"BREAD","amount":25,"meta":{"==":"ItemMeta","meta-type":"UNSPECIFIC","display-name":"§8[§4§lKit PvP§8]","lore":["§8Bread"]}},"0":{"==":"org.bukkit.inventory.ItemStack","type":"LEAVES","meta":{"==":"ItemMeta","meta-type":"UNSPECIFIC","display-name":"§8[§1§lTree§8]","lore":["§btim_de_doder's Leaves"],"enchants":{"DAMAGE_ALL":4}}}},"armorContents":{"3":{"==":"org.bukkit.inventory.ItemStack","type":"LEAVES","meta":{"==":"ItemMeta","meta-type":"UNSPECIFIC","display-name":"§8[§1§lTree§8]","lore":["§btim_de_doder's Leaves"],"enchants":{"PROTECTION_ENVIRONMENTAL":3}}},"2":{"==":"org.bukkit.inventory.ItemStack","type":"CHAINMAIL_CHESTPLATE","meta":{"==":"ItemMeta","meta-type":"UNSPECIFIC","display-name":"§8[§1§lTree§8]","lore":["§btim_de_doder's Chestplate"]}},"1":{"==":"org.bukkit.inventory.ItemStack","type":"CHAINMAIL_LEGGINGS","meta":{"==":"ItemMeta","meta-type":"UNSPECIFIC","display-name":"§8[§1§lTree§8]","lore":["§btim_de_doder's Leggings"]}},"0":{"==":"org.bukkit.inventory.ItemStack","type":"CHAINMAIL_BOOTS","meta":{"==":"ItemMeta","meta-type":"UNSPECIFIC","display-name":"§8[§1§lTree§8]","lore":["§btim_de_doder's Boots"]}}},"potions":"[]","enderChestContents":{},"stats":{"ra":"300","ex":"3.7187986","hp":"20","fl":"20","txp":"0","el":"0","sa":"2.0","ma":"300","xp":"0.0","ft":"-20","fd":"0.0"}}}