{"SURVIVAL":{"armorContents":{},"balance":"200.0","enderChestContents":{},"inventoryContents":{"2":{"==":"org.bukkit.inventory.ItemStack","type":"FENCE"},"1":{"==":"org.bukkit.inventory.ItemStack","type":"DIRT"},"0":{"==":"org.bukkit.inventory.ItemStack","type":"WOOD_PLATE","amount":2},"8":{"==":"org.bukkit.inventory.ItemStack","type":"WOOD","amount":38}},"potions":"[]","stats":{"ra":"300","ex":"0.0","hp":"20","txp":"32","fl":"20","el":"1","ma":"300","sa":"5.0","xp":"0.88235295","ft":"-20","fd":"0.0"}}}