{"SURVIVAL":{"potions":"[]","enderChestContents":{},"balance":"0.0","armorContents":{},"inventoryContents":{"1":{"==":"org.bukkit.inventory.ItemStack","type":"COAL_BLOCK","amount":2},"0":{"==":"org.bukkit.inventory.ItemStack","type":"WOOD_PICKAXE","damage":15},"30":{"==":"org.bukkit.inventory.ItemStack","type":"STICK","amount":2},"24":{"==":"org.bukkit.inventory.ItemStack","type":"WOOD","damage":3,"amount":3},"15":{"==":"org.bukkit.inventory.ItemStack","type":"WOOD","damage":3,"amount":3},"9":{"==":"org.bukkit.inventory.ItemStack","type":"SANDSTONE","amount":60},"26":{"==":"org.bukkit.inventory.ItemStack","type":"WOOD","damage":3},"11":{"==":"org.bukkit.inventory.ItemStack","type":"WOOD","damage":2,"amount":4},"12":{"==":"org.bukkit.inventory.ItemStack","type":"WORKBENCH"}},"stats":{"ra":"300","ex":"1.89465","hp":"20","txp":"0","fl":"20","el":"0","ma":"300","sa":"4.0","xp":"0.0","ft":"-20","fd":"0.0"}}}