{"SURVIVAL":{"inventoryContents":{"19":{"==":"org.bukkit.inventory.ItemStack","type":"ENDER_PEARL"},"35":{"==":"org.bukkit.inventory.ItemStack","type":"WOOD","amount":61},"17":{"==":"org.bukkit.inventory.ItemStack","type":"BED"},"18":{"==":"org.bukkit.inventory.ItemStack","type":"COBBLESTONE","amount":64},"33":{"==":"org.bukkit.inventory.ItemStack","type":"WOOD","amount":64},"15":{"==":"org.bukkit.inventory.ItemStack","type":"GLOWSTONE_DUST","amount":2},"34":{"==":"org.bukkit.inventory.ItemStack","type":"GRAVEL","amount":13},"16":{"==":"org.bukkit.inventory.ItemStack","type":"COBBLESTONE","amount":57},"13":{"==":"org.bukkit.inventory.ItemStack","type":"DIRT","amount":30},"14":{"==":"org.bukkit.inventory.ItemStack","type":"CARROT_ITEM"},"11":{"==":"org.bukkit.inventory.ItemStack","type":"SAND","amount":4},"12":{"==":"org.bukkit.inventory.ItemStack","type":"COBBLESTONE","amount":64},"21":{"==":"org.bukkit.inventory.ItemStack","type":"SAPLING","amount":2},"20":{"==":"org.bukkit.inventory.ItemStack","type":"LOG","amount":12},"22":{"==":"org.bukkit.inventory.ItemStack","type":"SULPHUR","amount":3},"23":{"==":"org.bukkit.inventory.ItemStack","type":"STICK","amount":4},"24":{"==":"org.bukkit.inventory.ItemStack","type":"BONE","amount":3},"25":{"==":"org.bukkit.inventory.ItemStack","type":"BOW","damage":286},"26":{"==":"org.bukkit.inventory.ItemStack","type":"INK_SACK","damage":4,"amount":29},"27":{"==":"org.bukkit.inventory.ItemStack","type":"ROTTEN_FLESH","amount":13},"28":{"==":"org.bukkit.inventory.ItemStack","type":"FLINT"},"29":{"==":"org.bukkit.inventory.ItemStack","type":"STONE_AXE","damage":50,"meta":{"==":"ItemMeta","meta-type":"UNSPECIFIC","display-name":"§bStarter Axe"}},"3":{"==":"org.bukkit.inventory.ItemStack","type":"COBBLESTONE","amount":28},"2":{"==":"org.bukkit.inventory.ItemStack","type":"INK_SACK","amount":3},"10":{"==":"org.bukkit.inventory.ItemStack","type":"COAL","amount":29},"1":{"==":"org.bukkit.inventory.ItemStack","type":"SPIDER_EYE","amount":13},"0":{"==":"org.bukkit.inventory.ItemStack","type":"TORCH","amount":8},"30":{"==":"org.bukkit.inventory.ItemStack","type":"STRING","amount":2},"7":{"==":"org.bukkit.inventory.ItemStack","type":"COBBLESTONE","amount":64},"6":{"==":"org.bukkit.inventory.ItemStack","type":"STONE_HOE","meta":{"==":"ItemMeta","meta-type":"UNSPECIFIC","display-name":"§bStarter Hoe"}},"32":{"==":"org.bukkit.inventory.ItemStack","type":"STONE_SPADE","damage":48,"meta":{"==":"ItemMeta","meta-type":"UNSPECIFIC","display-name":"§bStarter Shovel"}},"5":{"==":"org.bukkit.inventory.ItemStack","type":"WORKBENCH"},"31":{"==":"org.bukkit.inventory.ItemStack","type":"REDSTONE","amount":61},"9":{"==":"org.bukkit.inventory.ItemStack","type":"NETHERRACK","amount":25},"8":{"==":"org.bukkit.inventory.ItemStack","type":"BREAD","amount":4}},"enderChestContents":{},"balance":"0.0","potions":"[]","armorContents":{"0":{"==":"org.bukkit.inventory.ItemStack","type":"IRON_BOOTS","damage":12}},"stats":{"ex":"0.0612","ra":"300","hp":"20","txp":"307","fl":"20","el":"17","sa":"5.0","ma":"300","xp":"0.65217376","ft":"-20","fd":"0.0"}}}