{"SURVIVAL":{"balance":"0.0","inventoryContents":{"3":{"==":"org.bukkit.inventory.ItemStack","type":"FEATHER","amount":2},"2":{"==":"org.bukkit.inventory.ItemStack","type":"LEATHER","amount":3},"1":{"==":"org.bukkit.inventory.ItemStack","type":"ROTTEN_FLESH","amount":4},"0":{"==":"org.bukkit.inventory.ItemStack","type":"DIRT","amount":2},"7":{"==":"org.bukkit.inventory.ItemStack","type":"WORKBENCH"},"6":{"==":"org.bukkit.inventory.ItemStack","type":"DOUBLE_PLANT","damage":5,"amount":4},"5":{"==":"org.bukkit.inventory.ItemStack","type":"BROWN_MUSHROOM"},"4":{"==":"org.bukkit.inventory.ItemStack","type":"WOOL"},"8":{"==":"org.bukkit.inventory.ItemStack","type":"RAW_BEEF","amount":2}},"armorContents":{"2":{"==":"org.bukkit.inventory.ItemStack","type":"GOLD_CHESTPLATE","damage":104}},"potions":"[]","enderChestContents":{},"stats":{"ra":"300","ex":"3.6971626","hp":"20","fl":"19","txp":"59","el":"3","ma":"300","sa":"5.2000003","xp":"0.4705884","ft":"-20","fd":"0.0"}}}