{"SURVIVAL":{"enderChestContents":{},"armorContents":{},"potions":"[]","inventoryContents":{"3":{"==":"org.bukkit.inventory.ItemStack","type":"IRON_ORE","amount":25},"2":{"==":"org.bukkit.inventory.ItemStack","type":"BREAD","amount":28},"1":{"==":"org.bukkit.inventory.ItemStack","type":"WOOD_PICKAXE","damage":26},"0":{"==":"org.bukkit.inventory.ItemStack","type":"COBBLESTONE","amount":64},"7":{"==":"org.bukkit.inventory.ItemStack","type":"STONE_PICKAXE","meta":{"==":"ItemMeta","meta-type":"UNSPECIFIC","display-name":"§bStarter Pickaxe"}},"6":{"==":"org.bukkit.inventory.ItemStack","type":"TORCH","amount":3},"5":{"==":"org.bukkit.inventory.ItemStack","type":"COBBLESTONE","amount":27},"31":{"==":"org.bukkit.inventory.ItemStack","type":"STICK","amount":5},"4":{"==":"org.bukkit.inventory.ItemStack","type":"IRON_PICKAXE","damage":206},"8":{"==":"org.bukkit.inventory.ItemStack","type":"STONE_AXE","meta":{"==":"ItemMeta","meta-type":"UNSPECIFIC","display-name":"§bStarter Axe"}}},"balance":"293.0","stats":{"ra":"300","ex":"0.86278903","hp":"20","txp":"41","fl":"15","el":"2","ma":"300","sa":"0.0","xp":"0.4117647","ft":"-20","fd":"0.0"}}}