{"SURVIVAL":{"armorContents":{"3":{"==":"org.bukkit.inventory.ItemStack","type":"DIAMOND_HELMET","damage":59},"2":{"==":"org.bukkit.inventory.ItemStack","type":"DIAMOND_CHESTPLATE","damage":59},"1":{"==":"org.bukkit.inventory.ItemStack","type":"DIAMOND_LEGGINGS","damage":59},"0":{"==":"org.bukkit.inventory.ItemStack","type":"DIAMOND_BOOTS","damage":59}},"enderChestContents":{},"potions":"[]","inventoryContents":{"15":{"==":"org.bukkit.inventory.ItemStack","type":"SEEDS"},"13":{"==":"org.bukkit.inventory.ItemStack","type":"LOG","amount":53},"14":{"==":"org.bukkit.inventory.ItemStack","type":"APPLE","amount":4},"11":{"==":"org.bukkit.inventory.ItemStack","type":"LOG","amount":64},"12":{"==":"org.bukkit.inventory.ItemStack","type":"SAPLING","amount":13},"3":{"==":"org.bukkit.inventory.ItemStack","type":"STONE_PICKAXE","damage":53,"meta":{"==":"ItemMeta","meta-type":"UNSPECIFIC","display-name":"§bStarter Pickaxe"}},"2":{"==":"org.bukkit.inventory.ItemStack","type":"STONE_SPADE","damage":72,"meta":{"==":"ItemMeta","meta-type":"UNSPECIFIC","display-name":"§bStarter Shovel"}},"1":{"==":"org.bukkit.inventory.ItemStack","type":"DIAMOND_SWORD","damage":56,"meta":{"==":"ItemMeta","meta-type":"UNSPECIFIC","enchants":{"DAMAGE_ALL":2},"repair-cost":2}},"10":{"==":"org.bukkit.inventory.ItemStack","type":"PORK","amount":3},"0":{"==":"org.bukkit.inventory.ItemStack","type":"LOG","amount":64},"7":{"==":"org.bukkit.inventory.ItemStack","type":"LOG","damage":2,"amount":48},"6":{"==":"org.bukkit.inventory.ItemStack","type":"BAKED_POTATO","amount":6},"5":{"==":"org.bukkit.inventory.ItemStack","type":"DIAMOND_AXE","damage":272,"meta":{"==":"ItemMeta","meta-type":"UNSPECIFIC","enchants":{"DIG_SPEED":2},"repair-cost":2}},"4":{"==":"org.bukkit.inventory.ItemStack","type":"STONE_AXE","damage":52,"meta":{"==":"ItemMeta","meta-type":"UNSPECIFIC","display-name":"§bStarter Axe"}},"9":{"==":"org.bukkit.inventory.ItemStack","type":"SAPLING","damage":2},"8":{"==":"org.bukkit.inventory.ItemStack","type":"DIAMOND_PICKAXE","damage":374}},"bedSpawnLocation":{"ya":0.0,"wo":"SurvivalWorld","pi":0.0,"z":1733.0,"y":64.0,"x":1054.0},"balance":"1975.4753970402346","stats":{"ra":"300","ex":"1.8459401","hp":"20","txp":"293","fl":"20","el":"17","sa":"3.0","ma":"300","xp":"0.043478634","ft":"-20","fd":"0.0"}}}