{"SURVIVAL":{"inventoryContents":{"2":{"==":"org.bukkit.inventory.ItemStack","type":"FIREWORK","amount":64,"meta":{"==":"ItemMeta","meta-type":"FIREWORK","firework-effects":[{"==":"Firework","flicker":false,"trail":true,"colors":[{"==":"Color","RED":123,"BLUE":190,"GREEN":47},{"==":"Color","RED":235,"BLUE":68,"GREEN":136},{"==":"Color","RED":222,"BLUE":42,"GREEN":207},{"==":"Color","RED":179,"BLUE":44,"GREEN":49},{"==":"Color","RED":102,"BLUE":211,"GREEN":137},{"==":"Color","RED":240,"BLUE":240,"GREEN":240},{"==":"Color","RED":65,"BLUE":52,"GREEN":205}],"fade-colors":[],"type":"BALL"}],"power":1}},"1":{"==":"org.bukkit.inventory.ItemStack","type":"LEVER"},"0":{"==":"org.bukkit.inventory.ItemStack","type":"DIAMOND_AXE","meta":{"==":"ItemMeta","meta-type":"UNSPECIFIC","enchants":{"ARROW_INFINITE":1,"DAMAGE_ALL":5,"PROTECTION_FIRE":4,"FIRE_ASPECT":2,"THORNS":3},"repair-cost":10}}},"enderChestContents":{},"potions":"[]","armorContents":{"3":{"==":"org.bukkit.inventory.ItemStack","type":"GOLD_HELMET","meta":{"==":"ItemMeta","meta-type":"UNSPECIFIC","enchants":{"PROTECTION_PROJECTILE":4,"PROTECTION_FALL":4,"KNOCKBACK":2},"repair-cost":8}},"2":{"==":"org.bukkit.inventory.ItemStack","type":"DIAMOND_CHESTPLATE","meta":{"==":"ItemMeta","meta-type":"UNSPECIFIC","enchants":{"PROTECTION_FIRE":4,"KNOCKBACK":2,"PROTECTION_FALL":4},"repair-cost":6}},"1":{"==":"org.bukkit.inventory.ItemStack","type":"DIAMOND_LEGGINGS","meta":{"==":"ItemMeta","meta-type":"UNSPECIFIC","enchants":{"PROTECTION_FIRE":4,"PROTECTION_FALL":4,"ARROW_KNOCKBACK":2},"repair-cost":6}},"0":{"==":"org.bukkit.inventory.ItemStack","type":"DIAMOND_BOOTS","meta":{"==":"ItemMeta","meta-type":"UNSPECIFIC","enchants":{"ARROW_KNOCKBACK":2,"PROTECTION_FIRE":4},"repair-cost":8}}},"balance":"0.0","stats":{"ex":"0.0","ra":"300","hp":"20","txp":"0","fl":"20","el":"0","ma":"300","sa":"5.0","xp":"0.0","ft":"-20","fd":"0.0"}}}