{"SURVIVAL":{"potions":"[]","enderChestContents":{},"armorContents":{"2":{"==":"org.bukkit.inventory.ItemStack","type":"IRON_CHESTPLATE","damage":59},"1":{"==":"org.bukkit.inventory.ItemStack","type":"IRON_LEGGINGS","damage":59},"0":{"==":"org.bukkit.inventory.ItemStack","type":"IRON_BOOTS","damage":59}},"balance":"1694.0","inventoryContents":{"35":{"==":"org.bukkit.inventory.ItemStack","type":"COAL","amount":12},"17":{"==":"org.bukkit.inventory.ItemStack","type":"ROTTEN_FLESH","amount":2},"33":{"==":"org.bukkit.inventory.ItemStack","type":"BREAD","amount":4},"15":{"==":"org.bukkit.inventory.ItemStack","type":"DIAMOND","amount":9},"34":{"==":"org.bukkit.inventory.ItemStack","type":"INK_SACK","damage":4,"amount":9},"16":{"==":"org.bukkit.inventory.ItemStack","type":"COBBLESTONE","amount":53},"13":{"==":"org.bukkit.inventory.ItemStack","type":"SULPHUR","amount":9},"14":{"==":"org.bukkit.inventory.ItemStack","type":"COBBLESTONE","amount":64},"11":{"==":"org.bukkit.inventory.ItemStack","type":"ARROW","amount":4},"12":{"==":"org.bukkit.inventory.ItemStack","type":"BONE","amount":2},"26":{"==":"org.bukkit.inventory.ItemStack","type":"GREEN_RECORD"},"27":{"==":"org.bukkit.inventory.ItemStack","type":"GOLD_BARDING"},"28":{"==":"org.bukkit.inventory.ItemStack","type":"GREEN_RECORD"},"29":{"==":"org.bukkit.inventory.ItemStack","type":"REDSTONE","amount":2},"3":{"==":"org.bukkit.inventory.ItemStack","type":"IRON_PICKAXE"},"2":{"==":"org.bukkit.inventory.ItemStack","type":"IRON_PICKAXE","damage":80},"10":{"==":"org.bukkit.inventory.ItemStack","type":"IRON_ORE","amount":6},"1":{"==":"org.bukkit.inventory.ItemStack","type":"IRON_PICKAXE","damage":128},"0":{"==":"org.bukkit.inventory.ItemStack","type":"DIAMOND_SWORD","damage":339},"7":{"==":"org.bukkit.inventory.ItemStack","type":"FLINT"},"30":{"==":"org.bukkit.inventory.ItemStack","type":"WHEAT","amount":2},"6":{"==":"org.bukkit.inventory.ItemStack","type":"GRAVEL","amount":3},"32":{"==":"org.bukkit.inventory.ItemStack","type":"SADDLE"},"5":{"==":"org.bukkit.inventory.ItemStack","type":"COBBLESTONE","amount":64},"4":{"==":"org.bukkit.inventory.ItemStack","type":"DIRT","amount":7},"31":{"==":"org.bukkit.inventory.ItemStack","type":"GOLDEN_APPLE"},"9":{"==":"org.bukkit.inventory.ItemStack","type":"SPIDER_EYE"},"8":{"==":"org.bukkit.inventory.ItemStack","type":"STRING","amount":11}},"stats":{"ex":"2.212852","ra":"300","hp":"9","fl":"6","txp":"849","el":"30","sa":"0.0","ma":"300","xp":"0.387097","ft":"-20","fd":"0.0"}}}