{"SURVIVAL":{"enderChestContents":{},"armorContents":{},"balance":"1100.0","potions":"[]","inventoryContents":{"13":{"==":"org.bukkit.inventory.ItemStack","type":"STONE_PICKAXE","meta":{"==":"ItemMeta","meta-type":"UNSPECIFIC","display-name":"§bStarter Pickaxe"}},"27":{"==":"org.bukkit.inventory.ItemStack","type":"ARROW","amount":2},"14":{"==":"org.bukkit.inventory.ItemStack","type":"STONE_AXE","meta":{"==":"ItemMeta","meta-type":"UNSPECIFIC","display-name":"§bStarter Axe"}},"11":{"==":"org.bukkit.inventory.ItemStack","type":"STONE_SWORD","meta":{"==":"ItemMeta","meta-type":"UNSPECIFIC","display-name":"§bStarter Sword"}},"12":{"==":"org.bukkit.inventory.ItemStack","type":"STONE_SPADE","meta":{"==":"ItemMeta","meta-type":"UNSPECIFIC","display-name":"§bStarter Shovel"}},"3":{"==":"org.bukkit.inventory.ItemStack","type":"STONE_AXE","meta":{"==":"ItemMeta","meta-type":"UNSPECIFIC","display-name":"§bStarter Axe","enchants":{"DIG_SPEED":1}}},"2":{"==":"org.bukkit.inventory.ItemStack","type":"STONE_PICKAXE","meta":{"==":"ItemMeta","meta-type":"UNSPECIFIC","display-name":"§bStarter Pickaxe","enchants":{"DIG_SPEED":1}}},"1":{"==":"org.bukkit.inventory.ItemStack","type":"STONE_SWORD","damage":9,"meta":{"==":"ItemMeta","meta-type":"UNSPECIFIC","display-name":"§bStarter Sword","enchants":{"DAMAGE_ALL":1}}},"0":{"==":"org.bukkit.inventory.ItemStack","type":"BOW","damage":60,"meta":{"==":"ItemMeta","meta-type":"UNSPECIFIC","enchants":{"ARROW_DAMAGE":1}}},"7":{"==":"org.bukkit.inventory.ItemStack","type":"BOW","damage":190},"6":{"==":"org.bukkit.inventory.ItemStack","type":"DIAMOND_PICKAXE","damage":1152,"meta":{"==":"ItemMeta","meta-type":"UNSPECIFIC","enchants":{"DIG_SPEED":1}}},"5":{"==":"org.bukkit.inventory.ItemStack","type":"COOKIE","amount":3},"4":{"==":"org.bukkit.inventory.ItemStack","type":"BREAD","amount":20},"9":{"==":"org.bukkit.inventory.ItemStack","type":"STONE_HOE","meta":{"==":"ItemMeta","meta-type":"UNSPECIFIC","display-name":"§bStarter Hoe"}},"8":{"==":"org.bukkit.inventory.ItemStack","type":"ROTTEN_FLESH","amount":3}},"stats":{"ex":"0.0","ra":"300","hp":"20","fl":"20","txp":"18","el":"1","sa":"5.0","ma":"300","xp":"0.058823586","ft":"0","fd":"0.0"}}}