{"SURVIVAL":{"potions":"[]","inventoryContents":{"35":{"==":"org.bukkit.inventory.ItemStack","type":"BREAD","amount":6},"15":{"==":"org.bukkit.inventory.ItemStack","type":"STICK","amount":8},"34":{"==":"org.bukkit.inventory.ItemStack","type":"DIRT","amount":6},"16":{"==":"org.bukkit.inventory.ItemStack","type":"ROTTEN_FLESH"},"13":{"==":"org.bukkit.inventory.ItemStack","type":"TORCH"},"14":{"==":"org.bukkit.inventory.ItemStack","type":"WOOD","damage":4,"amount":24},"11":{"==":"org.bukkit.inventory.ItemStack","type":"INK_SACK","amount":3},"12":{"==":"org.bukkit.inventory.ItemStack","type":"COBBLESTONE","amount":2},"3":{"==":"org.bukkit.inventory.ItemStack","type":"STONE_SPADE","damage":9,"meta":{"==":"ItemMeta","meta-type":"UNSPECIFIC","display-name":"§bStarter Shovel"}},"2":{"==":"org.bukkit.inventory.ItemStack","type":"STONE_AXE","damage":9,"meta":{"==":"ItemMeta","meta-type":"UNSPECIFIC","display-name":"§bStarter Axe"}},"1":{"==":"org.bukkit.inventory.ItemStack","type":"STONE_PICKAXE","damage":11,"meta":{"==":"ItemMeta","meta-type":"UNSPECIFIC","display-name":"§bStarter Pickaxe"}},"10":{"==":"org.bukkit.inventory.ItemStack","type":"BONE","amount":4},"0":{"==":"org.bukkit.inventory.ItemStack","type":"STONE_SWORD","damage":16,"meta":{"==":"ItemMeta","meta-type":"UNSPECIFIC","display-name":"§bStarter Sword"}},"7":{"==":"org.bukkit.inventory.ItemStack","type":"FURNACE"},"6":{"==":"org.bukkit.inventory.ItemStack","type":"SPIDER_EYE"},"5":{"==":"org.bukkit.inventory.ItemStack","type":"STRING","amount":2},"4":{"==":"org.bukkit.inventory.ItemStack","type":"STONE_HOE","damage":9,"meta":{"==":"ItemMeta","meta-type":"UNSPECIFIC","display-name":"§bStarter Hoe"}},"9":{"==":"org.bukkit.inventory.ItemStack","type":"ARROW","amount":3}},"balance":"0.0","enderChestContents":{},"armorContents":{},"stats":{"ra":"300","ex":"1.9564223","hp":"20","fl":"20","txp":"23","el":"1","ma":"300","sa":"0.0","xp":"0.35294124","ft":"-20","fd":"0.0"}}}