{"SURVIVAL":{"balance":"0.0","potions":"[]","inventoryContents":{"19":{"==":"org.bukkit.inventory.ItemStack","type":"SULPHUR","amount":4},"35":{"==":"org.bukkit.inventory.ItemStack","type":"STONE_SPADE","damage":130,"meta":{"==":"ItemMeta","meta-type":"UNSPECIFIC","display-name":"§bStarter Shovel"}},"17":{"==":"org.bukkit.inventory.ItemStack","type":"PORK","amount":15},"18":{"==":"org.bukkit.inventory.ItemStack","type":"LOG","amount":6},"33":{"==":"org.bukkit.inventory.ItemStack","type":"FISHING_ROD"},"15":{"==":"org.bukkit.inventory.ItemStack","type":"YELLOW_FLOWER","amount":2},"34":{"==":"org.bukkit.inventory.ItemStack","type":"STONE_PICKAXE","damage":38,"meta":{"==":"ItemMeta","meta-type":"UNSPECIFIC","display-name":"§bStarter Pickaxe"}},"16":{"==":"org.bukkit.inventory.ItemStack","type":"INK_SACK","amount":2},"13":{"==":"org.bukkit.inventory.ItemStack","type":"RED_ROSE"},"14":{"==":"org.bukkit.inventory.ItemStack","type":"RAW_CHICKEN","amount":22},"11":{"==":"org.bukkit.inventory.ItemStack","type":"WOOL","amount":5},"12":{"==":"org.bukkit.inventory.ItemStack","type":"LEASH"},"21":{"==":"org.bukkit.inventory.ItemStack","type":"CACTUS","amount":3},"20":{"==":"org.bukkit.inventory.ItemStack","type":"SAND","amount":5},"22":{"==":"org.bukkit.inventory.ItemStack","type":"SUGAR_CANE","amount":8},"23":{"==":"org.bukkit.inventory.ItemStack","type":"COAL","amount":28},"24":{"==":"org.bukkit.inventory.ItemStack","type":"RAW_BEEF"},"25":{"==":"org.bukkit.inventory.ItemStack","type":"LEATHER","amount":2},"26":{"==":"org.bukkit.inventory.ItemStack","type":"COBBLESTONE","amount":2},"27":{"==":"org.bukkit.inventory.ItemStack","type":"ROTTEN_FLESH","amount":6},"28":{"==":"org.bukkit.inventory.ItemStack","type":"IRON_INGOT"},"29":{"==":"org.bukkit.inventory.ItemStack","type":"RED_ROSE","damage":8},"3":{"==":"org.bukkit.inventory.ItemStack","type":"STONE_AXE","damage":59,"meta":{"==":"ItemMeta","meta-type":"UNSPECIFIC","display-name":"§bStarter Axe"}},"2":{"==":"org.bukkit.inventory.ItemStack","type":"STONE_SPADE","damage":10,"meta":{"==":"ItemMeta","meta-type":"UNSPECIFIC","display-name":"§bStarter Shovel"}},"10":{"==":"org.bukkit.inventory.ItemStack","type":"BONE","amount":3},"1":{"==":"org.bukkit.inventory.ItemStack","type":"STONE_PICKAXE","damage":26,"meta":{"==":"ItemMeta","meta-type":"UNSPECIFIC","display-name":"§bStarter Pickaxe"}},"0":{"==":"org.bukkit.inventory.ItemStack","type":"STONE_SWORD","damage":71,"meta":{"==":"ItemMeta","meta-type":"UNSPECIFIC","display-name":"§bStarter Sword"}},"30":{"==":"org.bukkit.inventory.ItemStack","type":"SAPLING","damage":5,"amount":2},"7":{"==":"org.bukkit.inventory.ItemStack","type":"STICK","amount":4},"6":{"==":"org.bukkit.inventory.ItemStack","type":"WOOD","damage":5,"amount":22},"32":{"==":"org.bukkit.inventory.ItemStack","type":"CARROT_ITEM"},"5":{"==":"org.bukkit.inventory.ItemStack","type":"SEEDS","amount":52},"31":{"==":"org.bukkit.inventory.ItemStack","type":"FENCE","amount":19},"4":{"==":"org.bukkit.inventory.ItemStack","type":"STONE_HOE","meta":{"==":"ItemMeta","meta-type":"UNSPECIFIC","display-name":"§bStarter Hoe"}},"9":{"==":"org.bukkit.inventory.ItemStack","type":"ARROW","amount":9},"8":{"==":"org.bukkit.inventory.ItemStack","type":"FEATHER","amount":14}},"enderChestContents":{},"armorContents":{},"stats":{"ra":"300","ex":"2.539405","hp":"20","fl":"18","txp":"0","el":"0","ma":"300","sa":"4.0","xp":"0.0","ft":"-20","fd":"0.0"}}}