{"SURVIVAL":{"enderChestContents":{},"armorContents":{},"potions":"[]","inventoryContents":{"13":{"==":"org.bukkit.inventory.ItemStack","type":"FURNACE","amount":2},"11":{"==":"org.bukkit.inventory.ItemStack","type":"WATER","amount":6},"12":{"==":"org.bukkit.inventory.ItemStack","type":"FISHING_ROD"},"3":{"==":"org.bukkit.inventory.ItemStack","type":"BREAD","amount":16},"2":{"==":"org.bukkit.inventory.ItemStack","type":"COOKIE","amount":4},"1":{"==":"org.bukkit.inventory.ItemStack","type":"ENDER_PEARL"},"10":{"==":"org.bukkit.inventory.ItemStack","type":"GOLDEN_APPLE","amount":2},"0":{"==":"org.bukkit.inventory.ItemStack","type":"WOOD","damage":5},"7":{"==":"org.bukkit.inventory.ItemStack","type":"DIAMOND_HELMET","damage":7},"6":{"==":"org.bukkit.inventory.ItemStack","type":"LAVA","amount":2},"5":{"==":"org.bukkit.inventory.ItemStack","type":"LEATHER_HELMET"},"4":{"==":"org.bukkit.inventory.ItemStack","type":"REDSTONE","amount":10},"9":{"==":"org.bukkit.inventory.ItemStack","type":"STONE","amount":32},"8":{"==":"org.bukkit.inventory.ItemStack","type":"STONE_SWORD","damage":2}},"balance":"0.0","stats":{"ra":"300","ex":"1.3546041","hp":"20","fl":"20","txp":"0","el":"0","sa":"4.0","ma":"300","xp":"0.0","ft":"0","fd":"0.0"}}}